frameworks/__init__.py
frameworks/platforms/__init__.py
frameworks/settings/__init__.py
module/__init__.py
modules/__init__.py
tests/__init__.py
tests/module_test.py
afrinet_cloud_automator-0.0.3.dist-info/METADATA
afrinet_cloud_automator-0.0.3.dist-info/WHEEL
afrinet_cloud_automator-0.0.3.dist-info/entry_points.txt
afrinet_cloud_automator-0.0.3.dist-info/top_level.txt
afrinet_cloud_automator-0.0.3.dist-info/RECORD
